{
  "last_run": "2026-04-23T01:06:43Z",
  "run_id": "24810954892",
  "comments_made": {
    "198": "2026-04-23T01:06:43Z",
    "191": "2026-04-21T01:14:08Z",
    "120": "2026-04-19T12:29:00Z",
    "159": "2026-04-16T12:42:00Z",
    "99": "prior run"
  },
  "fix_attempts": {
    "test-handlerequest-error": {
      "pr_branch": "repo-assist/test-gateway-request-error-handling",
      "status": "open",
      "created": "2026-04-23T01:06:43Z",
      "description": "13 new tests for HandleRequestError paths"
    }
  },
  "notes": "Issue #198: root cause confirmed - _reconnectAttempts resets on TCP connect success even when auth fails at challenge/response stage. Proposed fix options A and B in comment. Future work: implement Option A fix. PR #195 superseded by #200 from AlexAlves87. PR #201 by shanselman addresses #199 setup wizard. New PR created this run for HandleRequestError test coverage.",
  "monthly_activity_issue": 127,
  "backlog_cursor": {
    "issues": 199,
    "prs": 201
  }
}
